{
    "lotr.menu.title": "Yüzüklerin Efendisi Modu: Orta Dünya Minecraft'ta - Yenilenmiş",
    "lotr.menu.subtitle": "Çalışma Halindeki 1.15 Güncellemesi",
    
	"block.lotr.gondor_rock": "Gondor Taşı",
	"block.lotr.gondor_brick": "Gondor Tuğlası",
	"block.lotr.mordor_rock": "Mordor Taşı",
	"block.lotr.mordor_brick": "Mordor Tuğlası",
	"block.lotr.rohan_rock": "Rohan Taşı",
	"block.lotr.rohan_brick": "Rohan Tuğlası",
	"block.lotr.blue_rock": "Luigon",
	"block.lotr.blue_brick": "Luigon Tuğla",
	"block.lotr.red_rock": "Cargon",
	"block.lotr.red_brick": "Cargon Tuğla",
	"block.lotr.simbelmyne": "Simbelmynë",
	"block.lotr.shire_heather": "Shire Fundası",
	"block.lotr.copper_ore": "Bakır Cevheri",
	"block.lotr.tin_ore": "Kalay Cevheri",
	"block.lotr.silver_ore": "Gümüş Cevheri",
	"block.lotr.mithril_ore": "Mithril Cevheri",
	"block.lotr.copper_block": "Bakır Blok",
	"block.lotr.tin_block": "Kalay Blok",
	"block.lotr.silver_block": "Gümüş Blok",
	"block.lotr.mithril_block": "Mithril Blok",
	"block.lotr.bronze_block": "Bronz Blok",
	"block.lotr.gondor_rock_slab": "Gondor Taşı Basamak",
	"block.lotr.gondor_rock_stairs": "Gondor Taşı Merdiven",
	"block.lotr.gondor_rock_wall": "Gondor Taşı Duvar",
	"block.lotr.gondor_crafting_table": "Gondor Çalışma Masası",
	"block.lotr.mordor_crafting_table": "Morgul Çalışma Masası",
	"block.lotr.rohan_crafting_table": "Rohirrim Çalışma Masası",
		"block.lotr.pine_log": "Çam Kütüğü",
    "block.lotr.pine_wood": "Çam Odunu",
    "block.lotr.pine_planks": "Çam Tahta",
    "block.lotr.pine_leaves": "Çam Yaprakları",
    "block.lotr.pine_sapling": "Çam Fidanı",
    "block.lotr.pine_slab": "Çam Basamak",
    "block.lotr.pine_stairs": "Çam Merdiven",
    "block.lotr.pine_fence": "Çam Çit",
    "block.lotr.pine_fence_gate": "Çam Çit Kapısı",
    "block.lotr.pine_door": "Çam Kapı",
    "block.lotr.pine_trapdoor": "Çam Tuzak Kapısı",
    "block.lotr.pine_pressure_plate": "Çam Basınç Plakası",
    "block.lotr.pine_button": "Çam Düğme",
    "block.lotr.stripped_pine_log": "Soyulmuş Çam Kütüğü",
    "block.lotr.stripped_pine_wood": "Soyulmuş Çam Odunu",
    "block.lotr.pine_beam": "Çam Kiriş",
    "block.lotr.pine_sign": "Çam Tabela",
    "block.lotr.mallorn_log": "Mallorn Kütüğü",
    "block.lotr.mallorn_wood": "Mallorn Odunu",
    "block.lotr.mallorn_planks": "Mallorn Tahta",
    "block.lotr.mallorn_leaves": "Mallorn Yaprakları",
    "block.lotr.mallorn_sapling": "Mallorn Fidanı",
    "block.lotr.mallorn_slab": "Mallorn Basamak",
    "block.lotr.mallorn_stairs": "Mallorn Merdiven",
    "block.lotr.mallorn_fence": "Mallorn Çit",
    "block.lotr.mallorn_fence_gate": "Mallorn Çit Kapısı",
    "block.lotr.mallorn_door": "Mallorn Kapı",
    "block.lotr.mallorn_trapdoor": "Mallorn Tuzak Kapısı",
    "block.lotr.mallorn_pressure_plate": "Mallorn Basınç Plakası",
    "block.lotr.mallorn_button": "Mallorn Düğme",
    "block.lotr.stripped_mallorn_log": "Soyulmuş Mallorn Kütüğü",
    "block.lotr.stripped_mallorn_wood": "Soyulmış Mallorn Odunu",
    "block.lotr.mallorn_beam": "Mallorn Kiriş",
    "block.lotr.mallorn_sign": "Mallorn Tabela",
	"block.lotr.dwarven_brick": "Cüce Tuğlası",
	"block.lotr.high_elven_brick": "Yüksek Elf Tuğlası",
	"block.lotr.galadhrim_brick": "Galadhrim Tuğlası",
	"block.lotr.wood_elven_brick": "Orman Elfi Tuğlası",
	"block.lotr.dwarven_crafting_table": "Cüce Çalışma Masası",
	"block.lotr.lindon_crafting_table": "Lindon Çalışma Masası",
	"block.lotr.rivendell_crafting_table": "Ayrıkvadi Çalışma Masası",
	"block.lotr.galadhrim_crafting_table": "Galadhrim Çalışma Masası",
	"block.lotr.wood_elven_crafting_table": "Orman Elfi Çalışma Masası",
	"block.lotr.apple_crumble": "Elmalı Kek",
	"block.lotr.salt_ore": "Tuz Cevheri",
	"block.lotr.sulfur_ore": "Sülfür Cevheri",
	"block.lotr.niter_ore": "Güherçile Cevheri",
	"block.lotr.salt_block": "Tuz Bloğu",
	"block.lotr.sulfur_block": "Sülfür Bloğu",
	"block.lotr.niter_block": "Güherçile Bloğu",
	"block.lotr.morgul_iron_ore_mordor": "Morgul Demiri Cevheri",
	"block.lotr.morgul_iron_ore_stone": "Morgul Demiri Cevheri",
	"block.lotr.durnor_ore": "Durnor Cevheri",
	"block.lotr.orc_steel_block": "Ork Çeliği Bloğu",
	"block.lotr.durnor_block": "Durnor Bloğu",
	"block.lotr.harad_brick": "Haradrim Tuğlası",
	"block.lotr.red_harad_brick": "Kırmızı Haradrim Tuğlası",
	"block.lotr.harad_crafting_table": "Haradrim Çalışma Masası",
	"block.lotr.gondor_brick_slab": "Gondor Tuğlası Basamak",
	"block.lotr.gondor_brick_stairs": "Gondor Tuğlası Merdiven",
	"block.lotr.gondor_brick_wall": "Gondor Tuğlası Duvar",
	"block.lotr.mordor_rock_slab": "Mordor Taşı Basamak",
	"block.lotr.mordor_rock_stairs": "Mordor Taşı Merdiven",
	"block.lotr.mordor_rock_wall": "Mordor Taşı Duvar",
	"block.lotr.mordor_brick_slab": "Mordor Tuğlası Basamak",
	"block.lotr.mordor_brick_stairs": "Mordor Tuğlası Merdiven",
	"block.lotr.mordor_brick_wall": "Mordor Tuğlası Duvar",
	"block.lotr.rohan_rock_slab": "Rohan Taşı Basamak",
    "block.lotr.rohan_rock_stairs": "Rohan Taşı Merdiven",
    "block.lotr.rohan_rock_wall": "Rohan Taşı Duvar",
    "block.lotr.rohan_brick_slab": "Rohan Tuğlası Basamak",
    "block.lotr.rohan_brick_stairs": "Rohan Tuğlası Merdiven",
    "block.lotr.rohan_brick_wall": "Rohan Tuğlası Duvar",
    "block.lotr.blue_rock_slab": "Luigon Basamak",
    "block.lotr.blue_rock_stairs": "Luigon Merdiven",
    "block.lotr.blue_rock_wall": "Luigon Duvar",
    "block.lotr.blue_brick_slab": "Luigon Tuğlası Basamak",
    "block.lotr.blue_brick_stairs": "Luigon Tuğlası Merdiven",
    "block.lotr.blue_brick_wall": "Luigon Tuğlası Duvar",
    "block.lotr.red_rock_slab": "Cargon Basamak",
    "block.lotr.red_rock_stairs": "Cargon Merdiven",
    "block.lotr.red_rock_wall": "Cargon Duvar",
    "block.lotr.red_brick_slab": "Cargon Tuğlası Basamak",
    "block.lotr.red_brick_stairs": "Cargon Tuğlası Merdiven",
    "block.lotr.red_brick_wall": "Cargon Tuğlası Duvar",
    "block.lotr.dwarven_brick_slab": "Cüce Tuğlası Basamak",
    "block.lotr.dwarven_brick_stairs": "Cüce Tuğlası Merdiven",
    "block.lotr.dwarven_brick_wall": "Cüce Tuğlası Duvar",
    "block.lotr.high_elven_brick_slab": "Yüksek Elf Tuğlası Basamak",
    "block.lotr.high_elven_brick_stairs": "Yüksek Elf Tuğlası Merdiven",
    "block.lotr.high_elven_brick_wall": "Yüksek Elf Tuğlası Duvar",
    "block.lotr.galadhrim_brick_slab": "Galadhrim Tuğlası Basamak",
    "block.lotr.galadhrim_brick_stairs": "Galadhrim Tuğlası Merdiven",
    "block.lotr.galadhrim_brick_wall": "Galadhrim Tuğlası Duvar",
    "block.lotr.wood_elven_brick_slab": "Orman Elfi Tuğlası Basamak",
    "block.lotr.wood_elven_brick_stairs": "Orman Elfi Tuğlası Merdiven",
    "block.lotr.wood_elven_brick_wall": "Orman Elfi Tuğlası Duvar",
    "block.lotr.harad_brick_slab": "Haradrim Tuğlası Basamak",
    "block.lotr.harad_brick_stairs": "Haradrim Tuğlası Merdiven",
    "block.lotr.harad_brick_wall": "Haradrim Tuğlası Duvar",
    "block.lotr.red_harad_brick_slab": "Kırmızı Haradrim Tuğlası Basamak",
    "block.lotr.red_harad_brick_stairs": "Kırmızı Haradrim Tuğlası Merdiven",
    "block.lotr.red_harad_brick_wall": "Kırmızı Haradrim Tuğlası Duvar",
    "block.lotr.dwarven_steel_block": "Cüce Çeliği Bloğu",
    "block.lotr.elven_steel_block": "Elf Çeliği Bloğu",
    "block.lotr.mirk_oak_log": "Kuyutorman Meşesi Kütüğü",
    "block.lotr.mirk_oak_wood": "Kuyutorman Meşesi Odunu",
    "block.lotr.mirk_oak_planks": "Kuyutorman Meşesi Tahta ",
    "block.lotr.mirk_oak_leaves": "Kuyutorman Meşesi Yaprakları",
    "block.lotr.mirk_oak_sapling": "Kuyutorman Meşesi Fidanı",
    "block.lotr.mirk_oak_slab": "Kuyutorman Meşesi Basamak",
    "block.lotr.mirk_oak_stairs": "Kuyutorman Meşesi Merdiven",
    "block.lotr.mirk_oak_fence": "Kuyutorman Meşesi Çit",
    "block.lotr.mirk_oak_fence_gate": "Kuyutorman Meşesi Çit Kapısı",
    "block.lotr.mirk_oak_door": "Kuyutorman Meşesi Kapı",
    "block.lotr.mirk_oak_trapdoor": "Kuyutorman Meşesi Tuzak Kapısı",
    "block.lotr.mirk_oak_pressure_plate": "Kuyutorman Meşesi Basınç Plakası",
    "block.lotr.mirk_oak_button": "Kuyutorman Meşesi Düğme",
    "block.lotr.stripped_mirk_oak_log": "Soyulmuş Kuyutorman Meşesi Kütüğü",
    "block.lotr.stripped_mirk_oak_wood": "Soyulmuş Kuyutorman Meşesi Odunu",
    "block.lotr.mirk_oak_beam": "Kuyutorman Meşesi Kiriş",
    "block.lotr.mirk_oak_sign": "Kuyutorman Meşesi Tabela",
    "block.lotr.charred_log": "Kömürleşmiş Kütük",
    "block.lotr.charred_wood": "Kömürleşmiş Odun",
    "block.lotr.charred_planks": "Kömürleşmiş Tahta",
    "block.lotr.charred_slab": "Kömürleşmiş Basamak",
    "block.lotr.charred_stairs": "Kömürleşmiş Merdiven",
    "block.lotr.charred_fence": "Kömürleşmiş Çit",
    "block.lotr.charred_fence_gate": "Kömürleşmiş Çit Kapısı",
    "block.lotr.charred_door": "Kömürleşmiş Kapı",
    "block.lotr.charred_trapdoor": "Kömürleşmiş Tuzak Kapısı",
    "block.lotr.charred_pressure_plate": "Kömürleşmiş Basınç Plakası",
    "block.lotr.charred_button": "Kömürleşmiş Düğme",
    "block.lotr.stripped_charred_log": "Kömürleşmiş Soyulmuş Kütük",
    "block.lotr.stripped_charred_wood": "Kömürleşmiş Soyulmuş Odun",
    "block.lotr.charred_beam": "Kömürleşmiş Kiriş",
    "block.lotr.charred_sign": "Kömürleşmiş Tabela",
    "block.lotr.apple_log": "Elma Kütüğü",
    "block.lotr.apple_wood": "Elma Odunu",
    "block.lotr.apple_planks": "Elma Tahta",
    "block.lotr.apple_leaves": "Elma Yaprakları",
    "block.lotr.apple_leaves_red": "Kırmızı Elma Yaprakları",
    "block.lotr.apple_leaves_green": "Yeşil Elma Yaprakları",
    "block.lotr.apple_sapling": "Elma Fidanı",
    "block.lotr.apple_slab": "Elma Basamak",
    "block.lotr.apple_stairs": "Elma Merdiven",
    "block.lotr.apple_fence": "Elma Çit",
    "block.lotr.apple_fence_gate": "Elma Çit Kapısı",
    "block.lotr.apple_door": "Elma Kapı",
    "block.lotr.apple_trapdoor": "Elma Tuzak Kapısı",
    "block.lotr.apple_pressure_plate": "Elma Basınç Plakası",
    "block.lotr.apple_button": "Elma Düğme",
    "block.lotr.stripped_apple_log": "Soyulmuş Elma Kütüğü",
    "block.lotr.stripped_apple_wood": "Soyulmuş Elma Odunu",
    "block.lotr.apple_beam": "Elma Kiriş",
    "block.lotr.apple_sign": "Elma Tabela",
    "block.lotr.pear_log": "Armut Kütüğü",
    "block.lotr.pear_wood": "Armut Odunu",
    "block.lotr.pear_planks": "Armut Tahta",
    "block.lotr.pear_leaves": "Armut Yaprakları",
    "block.lotr.pear_leaves_fruit": "Meyveli Armut Yaprakları",
    "block.lotr.pear_sapling": "Armut Fidanı",
    "block.lotr.pear_slab": "Armut Basamak",
    "block.lotr.pear_stairs": "Armut Merdiven",
    "block.lotr.pear_fence": "Armut Çit",
    "block.lotr.pear_fence_gate": "Armut Çit Kapısı",
    "block.lotr.pear_door": "Armut Kapı",
    "block.lotr.pear_trapdoor": "Armut Tuzak Kapısı",
    "block.lotr.pear_pressure_plate": "Armut Basınç Plakası",
    "block.lotr.pear_button": "Armut Düğme",
    "block.lotr.stripped_pear_log": "Soyulmuş Armut Kütüğü",
    "block.lotr.stripped_pear_wood": "Soyulmuş Armut Odunu",
    "block.lotr.pear_beam": "Armut Kiriş",
    "block.lotr.pear_sign": "Armut Tabela",
    "block.lotr.cherry_log": "Kiraz Kütüğü",
    "block.lotr.cherry_wood": "Kiraz Odunu",
    "block.lotr.cherry_planks": "Kiraz Tahta",
    "block.lotr.cherry_leaves": "Kiraz Yaprakları",
    "block.lotr.cherry_leaves_fruit": "Meyveli Kiraz Yaprakları",
    "block.lotr.cherry_sapling": "Kiraz Fidanı",
    "block.lotr.cherry_slab": "Kiraz Basamak",
    "block.lotr.cherry_stairs": "Kiraz Merdiven",
    "block.lotr.cherry_fence": "Kiraz Çit",
    "block.lotr.cherry_fence_gate": "Kiraz Çit Kapısı",
    "block.lotr.cherry_door": "Kiraz Kapı",
    "block.lotr.cherry_trapdoor": "Kiraz Tuzak Kapısı",
    "block.lotr.cherry_pressure_plate": "Kiraz Basınç Plakası",
    "block.lotr.cherry_button": "Kiraz Düğme",
    "block.lotr.stripped_cherry_log": "Soyulmuş Kiraz Kütüğü",
    "block.lotr.stripped_cherry_wood": "Soyulmış Kiraz Odunu",
    "block.lotr.cherry_beam": "Kiraz Kiriş",
    "block.lotr.cherry_sign": "Kiraz Tabela",
    "block.lotr.lebethron_log": "Lebethron Kütüğü",
    "block.lotr.lebethron_wood": "Lebethron Odunu",
    "block.lotr.lebethron_planks": "Lebethron Tahta",
    "block.lotr.lebethron_leaves": "Lebethron Yaprakları",
    "block.lotr.lebethron_sapling": "Lebethron Fidanı",
    "block.lotr.lebethron_slab": "Lebethron Basamak",
    "block.lotr.lebethron_stairs": "Lebethron Merdiven",
    "block.lotr.lebethron_fence": "Lebethron Çit",
    "block.lotr.lebethron_fence_gate": "Lebethron Çit Kapısı",
    "block.lotr.lebethron_door": "Lebethron Kapı",
    "block.lotr.lebethron_trapdoor": "Lebethron Tuzak Kapısı",
    "block.lotr.lebethron_pressure_plate": "Lebethron Basınç Plakası",
    "block.lotr.lebethron_button": "Lebethron Düğme",
    "block.lotr.stripped_lebethron_log": "Soyulmuş Lebethron Kütüğü",
    "block.lotr.stripped_lebethron_wood": "Soyulmuş Lebethron Odunu",
    "block.lotr.lebethron_beam": "Lebethron Kiriş",
    "block.lotr.lebethron_sign": "Lebethron Tabela",
    "block.lotr.beech_log": "Kayın Kütüğü",
    "block.lotr.beech_wood": "Kayın Odunu",
    "block.lotr.beech_planks": "Kayın Tahta",
    "block.lotr.beech_leaves": "Kayın Yaprakları",
    "block.lotr.beech_sapling": "Kayın Fidanı",
    "block.lotr.beech_slab": "Kayın Basamak",
    "block.lotr.beech_stairs": "Kayın Merdiven",
    "block.lotr.beech_fence": "Kayın Çit",
    "block.lotr.beech_fence_gate": "Kayın Çit Kapısı",
    "block.lotr.beech_door": "Kayın Kapı",
    "block.lotr.beech_trapdoor": "Kayın Tuzak Kapısı",
    "block.lotr.beech_pressure_plate": "Kayın Basınç Plakası",
    "block.lotr.beech_button": "Kayın Düğme",
    "block.lotr.stripped_beech_log": "Soyulmuş Kayın Kütüğü",
    "block.lotr.stripped_beech_wood": "Soyulmuş Kayın Odunu",
    "block.lotr.beech_beam": "Kayın Kiriş",
    "block.lotr.beech_sign": "Kayın Tabela",
    "block.lotr.cherry_pie": "Kirazlı Turta",
    "block.lotr.hearth_block": "Ocak Bloğu",
    "block.lotr.mallorn_ladder": "Mallorn Merdiven",
    "block.lotr.elanor": "Elanor",
    "block.lotr.niphredil": "Niphredil",
    "block.lotr.bluebell": "Çançiçeği",
    "block.lotr.marigold": "Kadife Çiçeği",
    "block.lotr.asphodel": "Çirişotu",
    "block.lotr.lavender": "Lavanta",
    "block.lotr.mordor_gravel": "Mordor Çakılı",
    "block.lotr.mordor_dirt": "Mordor Toprağı",
    "block.lotr.mordor_moss": "Solmuş Yosun",
    "block.lotr.mordor_grass": "Mordor Çimi",
    "block.lotr.mordor_thorn": "Diken",
    "block.lotr.dwarven_pillar": "Cüce Sütunu",
    "block.lotr.dwarven_pillar_slab": "Cüce Sütunu Basamak",
    "block.lotr.stone_pillar": "Taş Sütun",
    "block.lotr.stone_pillar_slab": "Taş Sütun Basamak",
    "block.lotr.gondor_pillar": "Gondor Sütunu",
    "block.lotr.gondor_pillar_slab": "Gondor Sütunu Basamak",
    "block.lotr.glowstone_ore": "Işıktaşı Cevheri",
    "block.lotr.glowing_dwarven_brick": "Parıltılı Cüce Tuğlası",
    "block.lotr.mordor_pillar": "Mordor Sütunu",
    "block.lotr.mordor_pillar_slab": "Mordor Sütunu Basamak",
    "block.lotr.rohan_pillar": "Rohan Sütunu",
    "block.lotr.rohan_pillar_slab": "Rohan Sütunu Basamak",
    "block.lotr.blue_pillar": "Luigon Sütun",
    "block.lotr.blue_pillar_slab": "Luigon Sütun Basamak",
    "block.lotr.red_pillar": "Cargon Sütun",
    "block.lotr.red_pillar_slab": "Cargon Sütun Basamak",
    "block.lotr.high_elven_pillar": "Yüksek Elf Sütunu",
    "block.lotr.high_elven_pillar_slab": "Yüksek Elf Sütunu Basamak",
    "block.lotr.galadhrim_pillar": "Galadhrim Sütunu",
    "block.lotr.galadhrim_pillar_slab": "Galadhrim Sütunu Basamak",
    "block.lotr.wood_elven_pillar": "Orman Elfi Sütunu",
    "block.lotr.wood_elven_pillar_slab": "Orman Elfi Sütunu Basamak",
    "block.lotr.harad_pillar": "Haradrim Sütunu",
    "block.lotr.harad_pillar_slab": "Haradrim Sütunu Basamak",
    "block.lotr.red_harad_pillar": "Kırmızı Haradrim Sütunu",
    "block.lotr.red_harad_pillar_slab": "Kırmızı Haradrim Sütunu Basamak",
    "block.lotr.umbar_brick": "Umbar Tuğlası",
    "block.lotr.umbar_brick_slab": "Umbar Tuğlası Basamak",
    "block.lotr.umbar_brick_stairs": "Umbar Tuğlası Merdiven",
    "block.lotr.umbar_brick_wall": "Umbar Tuğlası Duvar",
    "block.lotr.umbar_crafting_table": "Umbar Çalışma Masası",
    "block.lotr.umbar_pillar": "Umbar Sütunu",
    "block.lotr.umbar_pillar_slab": "Umbar Sütunu Basamak",
    "block.lotr.dripstone": "Damlataş",
    "block.lotr.mordor_dripstone": "Mordor Damlataşı",
    "block.lotr.obsidian_dripstone": "Obsidyen Damlataş",
    "block.lotr.ice_dripstone": "Buz Saçağı",
    "block.lotr.gondor_dripstone": "Gondor Damlataşı",
    "block.lotr.rohan_dripstone": "Rohan Damlataşı",
    "block.lotr.blue_dripstone": "Luigon Damlataş",
    "block.lotr.red_dripstone": "Cargon Damlataş",
    "block.lotr.andesite_dripstone": "Andezit Damlataş",
    "block.lotr.diorite_dripstone": "Diyorit Damlataş",
    "block.lotr.granite_dripstone": "Granit Damlataş",
    "block.lotr.oak_beam": "Meşe Kiriş",
    "block.lotr.spruce_beam": "Ladin Kiriş",
    "block.lotr.birch_beam": "Huş Kiriş",
    "block.lotr.jungle_beam": "Orman Ağacı Kiriş",
    "block.lotr.acacia_beam": "Akasya Kiriş",
    "block.lotr.dark_oak_beam": "Koyu Meşe Kiriş",
    "block.lotr.orc_torch": "Ork Meşalesi",
    "block.lotr.orc_bars": "Ork Çeliği Parmaklıklar",
    "block.lotr.dwarven_bars": "Cüce Çeliği Parmaklıklar",
    "block.lotr.bronze_bars": "Bronz Parmaklıklar",
    "block.lotr.silver_bars": "Gümüş Parmaklıklar",
    "block.lotr.gold_bars": "Altın Parmaklıklar",
    "block.lotr.mithril_bars": "Mithril Parmaklıklar",
    "block.lotr.high_elven_bars": "Çelik Yüksek Elf Parmaklıkları",
    "block.lotr.galadhrim_bars": "Çelik Galadhrim Parmaklıkları",
    "block.lotr.wood_elven_bars": "Çelik Orman Elfi Parmaklıkları",
    "block.lotr.high_elven_wood_bars": "Yüksek Elf Parmaklıkları",
    "block.lotr.galadhrim_wood_bars": "Galadhrim Parmaklıkları",
    "block.lotr.wood_elven_wood_bars": "Orman Elfi Parmaklıkları",
    "block.lotr.cracked_stone_brick_slab": "Çatlak Taş Tuğla Basamak",
    "block.lotr.cracked_stone_brick_stairs": "Çatlak Taş Tuğla Merdiven",
    "block.lotr.cracked_stone_brick_wall": "Çatlak Taş Tuğla Duvar",
    "block.lotr.clover": "Yonca",
    "block.lotr.four_leaf_clover": "Dört Yapraklı Yonca",
    "block.lotr.short_grass": "Kısa Çim",
    "block.lotr.wheatgrass": "Buğday Çimi",
    "block.lotr.flowery_grass": "Çiçekli Çim",
    "block.lotr.maple_log": "Akçaağaç Kütüğü",
    "block.lotr.maple_wood": "Akçaağaç Odunu",
    "block.lotr.maple_planks": "Akçaağaç Tahta",
    "block.lotr.maple_leaves": "Akçaağaç Yaprakları",
    "block.lotr.maple_sapling": "Akçaağaç Fidanı",
    "block.lotr.maple_slab": "Akçaağaç Basamak",
    "block.lotr.maple_stairs": "Akçaağaç Merdiven",
    "block.lotr.maple_fence": "Akçaağaç Çit",
    "block.lotr.maple_fence_gate": "Akçaağaç Çit Kapısı",
    "block.lotr.maple_door": "Akçaağaç Kapı",
    "block.lotr.maple_trapdoor": "Akçaağaç Tuzak Kapısı",
    "block.lotr.maple_pressure_plate": "Akçaağaç Basınç Plakası",
    "block.lotr.maple_button": "Akçaağaç Düğme",
    "block.lotr.stripped_maple_log": "Soyulmuş Akçaağaç Kütüğü",
    "block.lotr.stripped_maple_wood": "Soyulmuş Akçaağaç Odunu",
    "block.lotr.maple_beam": "Akçaağaç Kiriş",
    "block.lotr.maple_sign": "Akçaağaç Tabela",
    "block.lotr.thistle": "Devedikeni",
    "block.lotr.nettles": "Isırgan Otu",
    "block.lotr.fernsprout": "Eğrelti Otu",
    "block.lotr.candle": "Mum",
    "block.lotr.gold_chandelier": "Altın Avize",
    "block.lotr.iron_chandelier": "Demir Avize",
    "block.lotr.bronze_chandelier": "Bronz Avize",
    "block.lotr.silver_chandelier": "Gümüş Avize",
    "block.lotr.mithril_chandelier": "Mithril Avize",
    "block.lotr.athelas": "Athelas",
    "block.lotr.dwarfwort": "Cüceotu",
    "block.lotr.wild_pipeweed": "Vahşi Tütün",
    "block.lotr.wild_flax": "Vahşi Keten",
    "block.lotr.aspen_log": "Titrek Kavak Kütüğü",
    "block.lotr.aspen_wood": "Titrek Kavak Odunu",
    "block.lotr.aspen_planks": "Titrek Kavak Tahta",
    "block.lotr.aspen_leaves": "Titrek Kavak Yaprakları",
    "block.lotr.aspen_sapling": "Titrek Kavak Fidanı",
    "block.lotr.aspen_slab": "Titrek Kavak Basamak",
    "block.lotr.aspen_stairs": "Titrek Kavak Merdiven",
    "block.lotr.aspen_fence": "Titrek Kavak Çit",
    "block.lotr.aspen_fence_gate": "Titrek Kavak Çit Kapısı",
    "block.lotr.aspen_door": "Titrek Kavak Kapı",
    "block.lotr.aspen_trapdoor": "Titrek Kavak Tuzak Kapısı",
    "block.lotr.aspen_pressure_plate": "Titrek Kavak Basınç Plakası",
    "block.lotr.aspen_button": "Titrek Kavak Düğme",
    "block.lotr.stripped_aspen_log": "Soyulmuş Titrek Kavak Kütüğü",
    "block.lotr.stripped_aspen_wood": "Soyulmuş Titrek Kavak Odunu",
    "block.lotr.aspen_beam": "Titrek Kavak Kiriş",
    "block.lotr.aspen_sign": "Titrek Kavak Tabela",
    "block.lotr.lairelosse_log": "Lairelossë Kütüğü",
    "block.lotr.lairelosse_wood": "Lairelossë Odunu",
    "block.lotr.lairelosse_planks": "Lairelossë Tahta",
    "block.lotr.lairelosse_leaves": "Lairelossë Yaprakları",
    "block.lotr.lairelosse_sapling": "Lairelossë Fidanı",
    "block.lotr.lairelosse_slab": "Lairelossë Basamak",
    "block.lotr.lairelosse_stairs": "Lairelossë Merdiven",
    "block.lotr.lairelosse_fence": "Lairelossë Çit",
    "block.lotr.lairelosse_fence_gate": "Lairelossë Çit Kapısı",
    "block.lotr.lairelosse_door": "Lairelossë Kapı",
    "block.lotr.lairelosse_trapdoor": "Lairelossë Tuzak Kapısı",
    "block.lotr.lairelosse_pressure_plate": "Lairelossë Basınç Plakası",
    "block.lotr.lairelosse_button": "Lairelossë Düğme",
    "block.lotr.stripped_lairelosse_log": "Soyulmuş Lairelossë Kütüğü",
    "block.lotr.stripped_lairelosse_wood": "Soyulmuş Lairelossë Odunu",
    "block.lotr.lairelosse_beam": "Lairelossë Kiriş",
    "block.lotr.lairelosse_sign": "Lairelossë Tabela",
    "block.lotr.cedar_log": "Sedir Kütüğü",
    "block.lotr.cedar_wood": "Sedir Odunu",
    "block.lotr.cedar_planks": "Sedir Tahta",
    "block.lotr.cedar_leaves": "Sedir Yaprakları",
    "block.lotr.cedar_sapling": "Sedir Fidanı",
    "block.lotr.cedar_slab": "Sedir Basamak",
    "block.lotr.cedar_stairs": "Sedir Merdiven",
    "block.lotr.cedar_fence": "Sedir Çit",
    "block.lotr.cedar_fence_gate": "Sedir Çit Kapısı",
    "block.lotr.cedar_door": "Sedir Kapı",
    "block.lotr.cedar_trapdoor": "Sedir Tuzak Kapısı",
    "block.lotr.cedar_pressure_plate": "Sedir Basınç Plakası",
    "block.lotr.cedar_button": "Sedir Düğme",
    "block.lotr.stripped_cedar_log": "Soyulmuş Sedir Kütüğü",
    "block.lotr.stripped_cedar_wood": "Soyulmuş Sedir Odunu",
    "block.lotr.cedar_beam": "Sedir Kiriş",
    "block.lotr.cedar_sign": "Sedir Tabela",
    "block.lotr.blue_mallorn_torch": "Mavi Mallorn Meşalesi",
    "block.lotr.green_mallorn_torch": "Yeşil Mallorn Meşalesi",
    "block.lotr.gold_mallorn_torch": "Sarı Mallorn Meşalesi",
    "block.lotr.silver_mallorn_torch": "Gümüş Mallorn Meşalesi",
    "block.lotr.sandstone_dripstone": "Kumtaşı Damlataş",
    "block.lotr.red_sandstone_dripstone": "Kırmızı Kumtaşı Damlataş",
    "block.lotr.edhelvir_ore": "Edhelvir Cevheri",
    "block.lotr.edhelvir_block": "Edhelvir Bloğu",
    "block.lotr.high_elven_torch": "Yüksek Elf Meşalesi",
    "block.lotr.stone_wall": "Taş Duvar",
    "block.lotr.red_sand_gem": "Kırmızı Kum Cevheri",
    "block.lotr.yellow_sand_gem": "Sarı Kum Cevheri",
    "block.lotr.harad_daisy": "Harad Papatyası",
    "block.lotr.southbell": "Güney Çanı",
    "block.lotr.hibiscus": "Ebegümeci",
    "block.lotr.flame_of_harad": "Harad Alevi",
    "block.lotr.gulduril_ore_mordor": "Gulduril Cevheri",
    "block.lotr.gulduril_ore_stone": "Gulduril Cevheri",
    "block.lotr.gulduril_block": "Gulduril Bloğu",
    "block.lotr.edhelvir_crystal": "Edhelvir Kristali",
    "block.lotr.gulduril_crystal": "Gulduril Kristali",
    "block.lotr.glowstone_crystal": "Işık Taşı Kristali",
    "block.lotr.numenorean_brick": "Númenór Tuğlası",
    "block.lotr.numenorean_brick_slab": "Númenór Tuğlası Basamak",
    "block.lotr.numenorean_brick_stairs": "Númenór Tuğlası Merdiven",
    "block.lotr.numenorean_brick_wall": "Númenór Tuğlası Duvar",
    "block.lotr.numenorean_pillar": "Númenór Sütunu ",
    "block.lotr.numenorean_pillar_slab": "Númenór Sütunu Basamak",
    "block.lotr.alloy_forge": "Alaşım Ocağı",
    "block.lotr.dwarven_forge": "Cüce Ocağı",
    "block.lotr.elven_forge": "Elf Ocağı",
    "block.lotr.orc_forge": "Ork Ocağı",
    "block.lotr.uruk_brick": "Uruk Tuğlası",
    "block.lotr.uruk_brick_slab": "Uruk Tuğlası Basamak",
    "block.lotr.uruk_brick_stairs": "Uruk Tuğlası Merdiven",
    "block.lotr.uruk_brick_wall": "Uruk Tuğlası Duvar",
    "block.lotr.uruk_pillar": "Uruk Sütunu",
    "block.lotr.uruk_pillar_slab": "Uruk Sütunu Basamak",
    "block.lotr.uruk_crafting_table": "Uruk Çalışma Masası",
    "block.lotr.uruk_steel_block": "Uruk Çeliği Bloğu",
    "block.lotr.uruk_bars": "Uruk Çeliği Parmaklıklar",
    "block.lotr.hobbit_crafting_table": "Hobbit Çalışma Masası",
    "block.lotr.brick_pillar": "Tuğla Sütun",
    "block.lotr.brick_pillar_slab": "Tuğla Sütun Basamak",
    "block.lotr.shire_pine_door": "Shire Çamı Kapı",
    "block.lotr.shire_pine_trapdoor": "Shire Çamı Tuzak Kapısı",
    "block.lotr.fir_log": "Köknar Kütüğü",
    "block.lotr.fir_wood": "Köknar Odunu",
    "block.lotr.fir_planks": "Köknar Tahta",
    "block.lotr.fir_leaves": "Köknar Yaprakları",
    "block.lotr.fir_sapling": "Köknar Fidanı",
    "block.lotr.fir_slab": "Köknar Basamak",
    "block.lotr.fir_stairs": "Köknar Merdiven",
    "block.lotr.fir_fence": "Köknar Çit",
    "block.lotr.fir_fence_gate": "Köknar Çit Kapısı",
    "block.lotr.fir_door": "Köknar Kapı",
    "block.lotr.fir_trapdoor": "Köknar Tuzak Kapısı",
    "block.lotr.fir_pressure_plate": "Köknar Basınç Plakası",
    "block.lotr.fir_button": "Köknar Düğme",
    "block.lotr.stripped_fir_log": "Soyulmuş Köknar Kütüğü",
    "block.lotr.stripped_fir_wood": "Soyulmuş Köknar Odunu",
    "block.lotr.fir_beam": "Köknar Kiriş",
    "block.lotr.fir_sign": "Köknar Tabela",
    "block.lotr.larch_log": "Karaçam Kütüğü",
    "block.lotr.larch_wood": "Karaçam Odunu",
    "block.lotr.larch_planks": "Karaçam Tahta",
    "block.lotr.larch_leaves": "Karaçam Yaprakları",
    "block.lotr.larch_sapling": "Karaçam Fidanı",
    "block.lotr.larch_slab": "Karaçam Basamak",
    "block.lotr.larch_stairs": "Karaçam Merdiven",
    "block.lotr.larch_fence": "Karaçam Çit",
    "block.lotr.larch_fence_gate": "Karaçam Çit Kapısı",
    "block.lotr.larch_door": "Karaçam Kapı",
    "block.lotr.larch_trapdoor": "Karaçam Tuzak Kapısı",
    "block.lotr.larch_pressure_plate": "Karaçam Basınç Plakası",
    "block.lotr.larch_button": "Karaçam Düğme",
    "block.lotr.stripped_larch_log": "Soyulmuş Karaçam Kütüğü",
    "block.lotr.stripped_larch_wood": "Soyulmuş Karaçam Odunu",
    "block.lotr.larch_beam": "Karaçam Kiriş",
    "block.lotr.larch_sign": "Karaçam Tabela",
    "block.lotr.hobbit_oven": "Hobbit Ocağı",
    "block.lotr.fine_plate": "İnce Tabak",
    "block.lotr.stoneware_plate": "Seramik Tabak",
    "block.lotr.wooden_plate": "Tahta Tabak",
    "block.lotr.mossy_gondor_brick": "Yosunlu Gondor Tuğlası",
    "block.lotr.mossy_gondor_brick_slab": "Yosunlu Gondor Tuğlası Basamak",
    "block.lotr.mossy_gondor_brick_stairs": "Yosunlu Gondor Tuğlası Merdiven",
    "block.lotr.mossy_gondor_brick_wall": "Yosunlu Gondor Tuğlası Duvar",
    "block.lotr.cracked_gondor_brick": "Çatlak Gondor Tuğlası",
    "block.lotr.cracked_gondor_brick_slab": "Çatlak Gondor Tuğlası Basamak",
    "block.lotr.cracked_gondor_brick_stairs": "Çatlak Gondor Tuğlası Merdiven",
    "block.lotr.cracked_gondor_brick_wall": "Çatlak Gondor Tuğlası Duvar",
    "block.lotr.carved_gondor_brick": "Oyma Gondor Tuğlası",
    "block.lotr.mossy_high_elven_brick": "Yosunlu Yüksek Elf Tuğlası",
    "block.lotr.mossy_high_elven_brick_slab": "Yosunlu Yüksek Elf Tuğlası Basamak",
    "block.lotr.mossy_high_elven_brick_stairs": "Yosunlu Yüksek Elf Tuğlası Merdiven",
    "block.lotr.mossy_high_elven_brick_wall": "Yosunlu Yüksek Elf Tuğlası Duvar",
    "block.lotr.cracked_high_elven_brick": "Çatlak Yüksek Elf Tuğlası",
    "block.lotr.cracked_high_elven_brick_slab": "Çatlak Yüksek Elf Tuğlası Basamak",
    "block.lotr.cracked_high_elven_brick_stairs": "Çatlak Yüksek Elf Tuğlası Merdiven",
    "block.lotr.cracked_high_elven_brick_wall": "Çatlak Yüksek Elf Tuğlası Duvar",
    "block.lotr.carved_high_elven_brick": "Oyma Yüksek Elf Tuğlası",
    "block.lotr.thatch": "Saman",
    "block.lotr.thatch_slab": "Saman Basamak",
    "block.lotr.thatch_stairs": "Saman Merdiven",
    "block.lotr.drystone": "Kuru Duvar",
    "block.lotr.wattle_and_daub": "Dal Örgü",
    "block.lotr.wattle_and_daub_pillar": "Dal Örgü Yığını",
    "block.lotr.mossy_mordor_brick": "Yosunlu Mordor Tuğlası",
    "block.lotr.mossy_mordor_brick_slab": "Yosunlu Mordor Tuğlası Basamak",
    "block.lotr.mossy_mordor_brick_stairs": "Yosunlu Mordor Tuğlası Merdiven",
    "block.lotr.mossy_mordor_brick_wall": "Yosunlu Mordor Tuğlası Duvar",
    "block.lotr.cracked_mordor_brick": "Çatlak Mordor Tuğlası",
    "block.lotr.cracked_mordor_brick_slab": "Çatlak Mordor Tuğlası Basamak",
    "block.lotr.cracked_mordor_brick_stairs": "Çatlak Mordor Tuğlası Merdiven",
    "block.lotr.cracked_mordor_brick_wall": "Çatlak Mordor Tuğlası Duvar",
    "block.lotr.carved_mordor_brick": "Çatlak Mordor Tuğlası",
    "block.lotr.mossy_rohan_brick": "Yosunlu Rohan Tuğlası",
    "block.lotr.mossy_rohan_brick_slab": "Yosunlu Rohan Tuğlası Basamak",
    "block.lotr.mossy_rohan_brick_stairs": "Yosunlu Rohan Tuğlası Merdiven",
    "block.lotr.mossy_rohan_brick_wall": "Yosunlu Rohan Tuğlası Duvar",
    "block.lotr.cracked_rohan_brick": "Çatlak Rohan Tuğlası",
    "block.lotr.cracked_rohan_brick_slab": "Çatlak Rohan Tuğlası Basamak",
    "block.lotr.cracked_rohan_brick_stairs": "Çatlak Rohan Tuğlası Merdiven",
    "block.lotr.cracked_rohan_brick_wall": "Çatlak Rohan Tuğlası Duvar",
    "block.lotr.carved_rohan_brick": "Çatlak Rohan Tuğlası",
    "block.lotr.gold_trimmed_dwarven_brick": "Altın İşlemeli Cüce Tuğlası",
    "block.lotr.silver_trimmed_dwarven_brick": "Gümüş İşlemeli Cüce Tuğlası",
    "block.lotr.mithril_trimmed_dwarven_brick": "Mithril İşlemeli Cüce Tuğlası",
    "block.lotr.mossy_numenorean_brick": "Yosunlu Númenór Tuğlası",
    "block.lotr.mossy_numenorean_brick_slab": "Yosunlu Númenór Tuğlası Basamak",
    "block.lotr.mossy_numenorean_brick_stairs": "Yosunlu Númenór Tuğlası Merdiven",
    "block.lotr.mossy_numenorean_brick_wall": "Yosunlu Númenór Tuğlası Duvar",
    "block.lotr.cracked_numenorean_brick": "Çatlak Númenór Tuğlası",
    "block.lotr.cracked_numenorean_brick_slab": "Çatlak Númenór Tuğlası Basamak",
    "block.lotr.cracked_numenorean_brick_stairs": "Çatlak Númenór Tuğlası Merdiven",
    "block.lotr.cracked_numenorean_brick_wall": "Çatlak Númenór Tuğlası Duvar",
	
	"item.lotr.gold_ring": "Altın Yüzük",
	"item.lotr.copper_ingot": "Bakır Külçesi",
	"item.lotr.tin_ingot": "Kalay Külçesi",
	"item.lotr.silver_ingot": "Gümüş Külçesi",
	"item.lotr.mithril_ingot": "Mithril Külçesi",
	"item.lotr.bronze_ingot": "Bronz Külçesi",
	"item.lotr.silver_nugget": "Gümüş Parçası",
	"item.lotr.mithril_nugget": "Mithril Parçası",
	"item.lotr.silver_ring": "Gümüş Yüzük",
	"item.lotr.mithril_ring": "Mithril Yüzük",
	"item.lotr.mallorn_stick": "Mallorn Çubuk",
	"item.lotr.lembas": "Lembas",
	"item.lotr.gammon": "Tuzlanmış Domuz",
	"item.lotr.green_apple": "Yeşil Elma",
	"item.lotr.salt": "Tuz",
	"item.lotr.sulfur": "Sülfür",
	"item.lotr.niter": "Güherçile",
	"item.lotr.suspicious_meat": "Şüpheli Et",
	"item.lotr.fur": "Kürk",
	"item.lotr.red_book": "Kırmızı Kitap",
	"item.lotr.orc_steel_ingot": "Ork Çeliği",
	"item.lotr.durnor": "Durnor",
	"item.lotr.mithril_mail": "Mithril Örgü",
	"item.lotr.bronze_shovel": "Bronz Kürek",
	"item.lotr.bronze_pickaxe": "Bronz Kazma",
	"item.lotr.bronze_axe": "Bronz Balta",
	"item.lotr.bronze_sword": "Bronz Kılıç",
	"item.lotr.bronze_hoe": "Bronz Çapa",
	"item.lotr.mithril_shovel": "Mithril Kürek",
    "item.lotr.mithril_pickaxe": "Mithril Kazma",
    "item.lotr.mithril_axe": "Mithril Balta",
    "item.lotr.mithril_sword": "Mithril Kılıç",
    "item.lotr.mithril_hoe": "Mithril Çapa",
    "item.lotr.bronze_helmet": "Bronz Miğfer",
    "item.lotr.bronze_chestplate": "Bronz Göğüs Zırhı",
    "item.lotr.bronze_leggings": "Bronz Bacak Zırhı",
    "item.lotr.bronze_boots": "Bronz Botlar",
    "item.lotr.mithril_helmet": "Mithril Miğfer",
    "item.lotr.mithril_chestplate": "Mithril Göğüs Zırhı",
    "item.lotr.mithril_leggings": "Mithril Bacak Zırhı",
    "item.lotr.mithril_boots": "Mithril Botlar",
    "item.lotr.mordor_shovel": "Mordor Küreği",
    "item.lotr.mordor_pickaxe": "Mordor Kazması",
    "item.lotr.mordor_axe": "Mordor Baltası",
    "item.lotr.mordor_scimitar": "Mordor Palası",
    "item.lotr.mordor_hoe": "Mordor Çapası",
    "item.lotr.mordor_helmet": "Mordor Miğferi",
    "item.lotr.mordor_chestplate": "Mordor Göğüs Zırhı",
    "item.lotr.mordor_leggings": "Mordor Bacak Zırhı",
    "item.lotr.mordor_boots": "Mordor Botları",
    "item.lotr.gondor_sword": "Gondorlu Kılıcı",
    "item.lotr.gondor_helmet": "Gondorlu Miğferi",
    "item.lotr.gondor_chestplate": "Gondorlu Göğüs Zırhı",
    "item.lotr.gondor_leggings": "Gondorlu Bacak Zırhı",
    "item.lotr.gondor_boots": "Gondorlu Botu",
    "item.lotr.rohan_sword": "Rohanlı Kılıcı",
    "item.lotr.rohan_helmet": "Rohanlı Miğferi",
    "item.lotr.rohan_chestplate": "Rohanlı Zırh Yeleği",
    "item.lotr.rohan_leggings": "Rohanlı Bacak Zırhı",
    "item.lotr.rohan_boots": "Rohanlı Botları",
    "item.lotr.dwarven_steel_ingot": "Cüce Çeliği",
    "item.lotr.elven_steel_ingot": "Elf Çeliği",
    "item.lotr.dwarven_shovel": "Cüce Küreği",
    "item.lotr.dwarven_pickaxe": "Cüce Kazması",
    "item.lotr.dwarven_axe": "Cüce Baltası",
    "item.lotr.dwarven_sword": "Cüce Kılıcı",
    "item.lotr.dwarven_hoe": "Cüce Çapası",
    "item.lotr.dwarven_helmet": "Cüce Miğferi",
    "item.lotr.dwarven_chestplate": "Cüce Göğüs Zırhı",
    "item.lotr.dwarven_leggings": "Cüce Bacak Zırhı",
    "item.lotr.dwarven_boots": "Cüce Botları",
    "item.lotr.lindon_shovel": "Lindon Küreği",
    "item.lotr.lindon_pickaxe": "Lindon Kazması",
    "item.lotr.lindon_axe": "Lindon Baltası",
    "item.lotr.lindon_sword": "Lindon Kılıcı",
    "item.lotr.lindon_hoe": "Lindon Çapası",
    "item.lotr.lindon_helmet": "Lindon Miğferi",
    "item.lotr.lindon_chestplate": "Lindon Göğüs Zırhı",
    "item.lotr.lindon_leggings": "Lindon Bacak Zırhı",
    "item.lotr.lindon_boots": "Lindon Botları",
    "item.lotr.rivendell_shovel": "Ayrıkvadi Küreği",
    "item.lotr.rivendell_pickaxe": "Ayrıkvadi Kazması",
    "item.lotr.rivendell_axe": "Ayrıkvadi Baltası",
    "item.lotr.rivendell_sword": "Ayrıkvadi Kılıcı",
    "item.lotr.rivendell_hoe": "Ayrıkvadi Çapası",
    "item.lotr.rivendell_helmet": "Ayrıkvadi Miğferi",
    "item.lotr.rivendell_chestplate": "Ayrıkvadi Göğüs Zırhı",
    "item.lotr.rivendell_leggings": "Ayrıkvadi Bacak Zırhı",
    "item.lotr.rivendell_boots": "Ayrıkvadi Botları",
    "item.lotr.pear": "Armut",
    "item.lotr.cherry": "Kiraz",
    "item.lotr.galadhrim_shovel": "Galadhrim Küreği",
    "item.lotr.galadhrim_pickaxe": "Galadhrim Kazması",
    "item.lotr.galadhrim_axe": "Galadhrim Baltası",
    "item.lotr.galadhrim_sword": "Galadhrim Kılıcı",
    "item.lotr.galadhrim_hoe": "Galadhrim Çapası",
    "item.lotr.galadhrim_helmet": "Galadhrim Miğferi",
    "item.lotr.galadhrim_chestplate": "Galadhrim Göğüs Zırhı",
    "item.lotr.galadhrim_leggings": "Galadhrim Bacak Zırhı",
    "item.lotr.galadhrim_boots": "Galadhrim Botları",
    "item.lotr.wood_elven_shovel": "Orman Elfi Küreği",
    "item.lotr.wood_elven_pickaxe": "Orman Elfi Kazması",
    "item.lotr.wood_elven_axe": "Orman Elfi Baltası",
    "item.lotr.wood_elven_sword": "Orman Elfi Kılıcı",
    "item.lotr.wood_elven_hoe": "Orman Elfi Çapası",
    "item.lotr.wood_elven_helmet": "Orman Elfi Miğferi",
    "item.lotr.wood_elven_chestplate": "Orman Elfi Göğüs Zırhı",
    "item.lotr.wood_elven_leggings": "Orman Elfi Bacak Zırhı",
    "item.lotr.wood_elven_boots": "Orman Elfi Botları",
    "item.lotr.pocket_match": "Kibrit",
    "item.lotr.fur_helmet": "Kürk Şapka",
    "item.lotr.fur_chestplate": "Kürk Tünik",
    "item.lotr.fur_leggings": "Kürk Pantolon",
    "item.lotr.fur_boots": "Kürk Botlar",
    "item.lotr.harad_sword": "Haradrim Kılıcı",
    "item.lotr.harad_helmet": "Haradrim Miğferi",
    "item.lotr.harad_chestplate": "Haradrim Göğüs Zırhı ",
    "item.lotr.harad_leggings": "Haradrim Bacak Zırhı",
    "item.lotr.harad_boots": "Haradrim Botları",
    "item.lotr.harad_warlord_helmet": "Haradrim Savaş Lordu Miğferi",
    "item.lotr.umbar_scimitar": "Umbar Palası",
    "item.lotr.umbar_helmet": "Umbar Miğferi",
    "item.lotr.umbar_chestplate": "Umbar Göğüs Zırhı",
    "item.lotr.umbar_leggings": "Umbar Bacak Zırhı",
    "item.lotr.umbar_boots": "Umbar Botları",
    "item.lotr.maple_syrup": "Akçaağaç Pekmezi",
    "item.lotr.beeswax": "Balmumu",
    "item.lotr.pipeweed_seeds": "Pipo Otu Tohumu",
    "item.lotr.pipeweed_leaf": "Pipo Otu Yaprağı",
    "item.lotr.pipeweed": "Pipo Otu",
    "item.lotr.flax_seeds": "Keten Tohumu",
    "item.lotr.flax": "Keten",
    "item.lotr.lettuce": "Marul",
    "item.lotr.edhelvir": "Edhelvir",
    "item.lotr.gulduril": "Gulduril",
    "item.lotr.uruk_steel_ingot": "Uruk Çeliği Külçesi",
    "item.lotr.uruk_shovel": "Uruk Küreği",
    "item.lotr.uruk_pickaxe": "Uruk Kazması",
    "item.lotr.uruk_axe": "Uruk Baltası",
    "item.lotr.uruk_cleaver": "Uruk Satırı",
    "item.lotr.uruk_hoe": "Uruk Çapası",
    "item.lotr.uruk_helmet": "Uruk Miğferi",
    "item.lotr.uruk_chestplate": "Uruk Göğüs Zırhı",
    "item.lotr.uruk_leggings": "Uruk Bacak Zırhı",
    "item.lotr.uruk_boots": "Uruk Botları",
    "item.lotr.uruk_berserker_cleaver": "Uruk Berserker Satırı",
    "item.lotr.uruk_berserker_helmet": "Uruk Berserker Miğferi",
    "item.lotr.clay_plate": "Kil Tabak",
	
        "itemGroup.lotr.blocks": "Orta Dünya Blokları",
	"itemGroup.lotr.util": "Orta Dünya Araçları",
	"itemGroup.lotr.decorations": "Orta Dünya Dekorasyonları",
	"itemGroup.lotr.materials": "Orta Dünya Materyalleri",
	"itemGroup.lotr.misc": "Orta Dünya Ivır Zıvırları",
	"itemGroup.lotr.food": "Orta Dünya Yemekleri",
	"itemGroup.lotr.tools": "Orta Dünya Aletleri",
	"itemGroup.lotr.combat": "Orta Dünya Savaş Gereçleri",
	"itemGroup.lotr.story": "Orta Dünya Hikayesi",
	
	"container.lotr.gondor_crafting": "Gondor Üretimi",
	"container.lotr.mordor_crafting": "Morgul Üretimi",
	"container.lotr.rohan_crafting": "Rohan Üretimi",
	"container.lotr.dwarven_crafting": "Cüce Üretimi",
	"container.lotr.lindon_crafting": "Lindon Üretimi",
	"container.lotr.rivendell_crafting": "Ayrıkvadi Üretimi",
	"container.lotr.galadhrim_crafting": "Galadhrim Üretimi",
	"container.lotr.wood_elven_crafting": "Orman Elfi Üretimi",
	"container.lotr.harad_crafting": "Haradrim Üretimi",
	"container.lotr.umbar_crafting": "Umbar Üretimi",
	"container.lotr.uruk_crafting": "Uruk Üretimi",
	"container.lotr.hobbit_crafting": "Hobbit Üretimi",
	
	"container.lotr.alloy_forge": "Alaşım Ocağı",
	"container.lotr.dwarven_forge": "Cüce Ocağı",
	"container.lotr.elven_forge": "Elf Ocağı",
	"container.lotr.orc_forge": "Ork Ocağı",
	"container.lotr.hobbit_oven": "Hobbit Ocağı",
	
        "biome.lotr.shire": "Shire",
	"biome.lotr.mordor": "Mordor",
	"biome.lotr.gondor": "Gondor",
	"biome.lotr.rohan": "Rohan",
	"biome.lotr.misty_mountains": "Dumanlı Dağlar",
	"biome.lotr.shire_woodlands": "Shire Ormanlığı",
	"biome.lotr.trollshaws": "Trollbükü",
	"biome.lotr.blue_mountains": "Mavi Dağlar",
	"biome.lotr.eriador": "Eriador",
	"biome.lotr.lone_lands": "Yanlız Topraklar",
	"biome.lotr.ithilien": "Ithilien",
	"biome.lotr.brown_lands": "Boz Topraklar",
	"biome.lotr.lothlorien": "Lothlórien",
	"biome.lotr.iron_hills": "Demir Tepeler",
	"biome.lotr.dunland": "Dunland",
	"biome.lotr.emyn_muil": "Emyn Muil",
	"biome.lotr.lindon": "Lindon",
	"biome.lotr.southron_coasts": "Güney Kıyıları",
        "biome.lotr.nan_curunir": "Nan Curunír",
        "biome.lotr.forodwaith": "Forodwaith",
	
	"stat.lotr.interact_faction_crafting_table": "Çalışma masalarıyla yapılan etkileşimler",
	"stat.lotr.throw_ring_in_fire": "Ateşe Atılan Yüzükler",
	"stat.lotr.interact_dwarven_forge": "Cüce Ocağıyla yapılan etkileşimler",
	"stat.lotr.interact_elven_forge": "Elf Ocağıyla yapılan etkileşimler",
	"stat.lotr.interact_orc_forge": "Ork Ocağıyla yapılan etkileşimler",
	"stat.lotr.interact_hobbit_oven": "Hobbit Ocağıyla yapılan etkileşimler",
	
        "death.attack.lotr.plant": "%s bir bitki tarafından öldürüldü",
	"death.attack.lotr.frost": "%s soğuğa yenik düştü",
	"death.attack.lotr.poisonDrink": "%s yanlış içeceği içti",
	"death.attack.lotr.stalagmite": "%s bir dikit tarafından öldürüldü",
	
	"chat.lotr.res_pack_warning": "%s: Uyarı: Mod kaynakları varsayılan kaynaklardan düşük önceliğe ayarlandı. Bu sebeple modun dikey basamak gibi özellikleri bozulacak. Düzeltmek için, Ayarlar -> Kaynak Paketleri -> 'Mod Kaynakları'nı 'Varsayılan'ın üzerine taşıyınız."
}